portmgr/__init__.py
portmgr/__main__.py
portmgr/portmgr.py
portmgr/wrapper.py
portmgr/commands/__init__.py
portmgr/commands/attach.py
portmgr/commands/build.py
portmgr/commands/down.py
portmgr/commands/logs.py
portmgr/commands/ps.py
portmgr/commands/pull.py
portmgr/commands/push.py
portmgr/commands/scan.py
portmgr/commands/stats.py
portmgr/commands/stop.py
portmgr/commands/top.py
portmgr/commands/up.py
portmgr-1.8.2.dist-info/METADATA
portmgr-1.8.2.dist-info/WHEEL
portmgr-1.8.2.dist-info/entry_points.txt
portmgr-1.8.2.dist-info/licenses/LICENSE
portmgr-1.8.2.dist-info/RECORD
