Metadata-Version: 2.4
Name: portmgr
Version: 1.8.2
Summary: Simple command interface to manage multiple Docker container
Project-URL: Website, https://github.com/Craeckie/portmgr
Project-URL: Repository, https://github.com/Craeckie/portmgr.git
License-Expression: MIT
License-File: LICENSE
Requires-Python: >=3.11
Requires-Dist: humanfriendly~=10.0
Requires-Dist: jsonschema~=3.2.0
Requires-Dist: pyyaml~=6.0.2
Requires-Dist: tabulate~=0.8.9
